counterfactual_xai/__init__.py
counterfactual_xai/add.py
counterfactual_xai-0.0.4.dist-info/LICENSE
counterfactual_xai-0.0.4.dist-info/METADATA
counterfactual_xai-0.0.4.dist-info/WHEEL
counterfactual_xai-0.0.4.dist-info/top_level.txt
counterfactual_xai-0.0.4.dist-info/RECORD
